{
  "generated_at_utc": "2026-02-28T15:09:34.297Z",
  "season_start": "2025-11-14",
  "rows": [
    {
      "teamId": "675",
      "team": "Washburn",
      "conference": "mid-america-intercollegiate",
      "games": 26,
      "adjO": 119.57071715799844,
      "adjD": 85.13812301872719,
      "adjEM": 34.43259413927126,
      "adjT": 72.21346153846153
    },
    {
      "teamId": "2048",
      "team": "Nova Southeastern",
      "conference": "sunshine-state",
      "games": 24,
      "adjO": 125.4926045345207,
      "adjD": 94.41972277632858,
      "adjEM": 31.07288175819211,
      "adjT": 81.41250000000001
    },
    {
      "teamId": "2141",
      "team": "Gannon",
      "conference": "psac",
      "games": 27,
      "adjO": 117.67327835970582,
      "adjD": 88.29865197983523,
      "adjEM": 29.37462637987059,
      "adjT": 83.0925925925926
    },
    {
      "teamId": "2285",
      "team": "Northern Mich.",
      "conference": "gliac",
      "games": 29,
      "adjO": 127.05488994148789,
      "adjD": 100.76752333324418,
      "adjEM": 26.2873666082437,
      "adjT": 64.97327586206896
    },
    {
      "teamId": "1434",
      "team": "Anderson (SC)",
      "conference": "sac",
      "games": 27,
      "adjO": 121.38431790379227,
      "adjD": 97.32824427480915,
      "adjEM": 24.056073628983114,
      "adjT": 70.39166666666667
    },
    {
      "teamId": "1906",
      "team": "Fairmont St.",
      "conference": "mec",
      "games": 27,
      "adjO": 123.40414858662119,
      "adjD": 99.59609643511202,
      "adjEM": 23.808052151509173,
      "adjT": 73.83148148148149
    },
    {
      "teamId": "261790",
      "team": "Daemen",
      "conference": "ecc",
      "games": 27,
      "adjO": 115.7268494568029,
      "adjD": 92.43316719528772,
      "adjEM": 23.293682261515173,
      "adjT": 71.5925925925926
    },
    {
      "teamId": "261810",
      "team": "Walsh",
      "conference": "g-mac",
      "games": 26,
      "adjO": 120.28746938611634,
      "adjD": 98.02641222798204,
      "adjEM": 22.261057158134307,
      "adjT": 71.84711538461539
    },
    {
      "teamId": "2587",
      "team": "Saint Martin's",
      "conference": "great-northwest",
      "games": 27,
      "adjO": 117.07652258942612,
      "adjD": 95.11452403018667,
      "adjEM": 21.961998559239447,
      "adjT": 70.0712962962963
    },
    {
      "teamId": "880",
      "team": "Lenoir-Rhyne",
      "conference": "sac",
      "games": 27,
      "adjO": 122.92831224870059,
      "adjD": 101.04747320061256,
      "adjEM": 21.880839048088035,
      "adjT": 75.53333333333333
    },
    {
      "teamId": "191",
      "team": "West Liberty",
      "conference": "mec",
      "games": 27,
      "adjO": 118.69959955432492,
      "adjD": 97.06973740381142,
      "adjEM": 21.629862150513503,
      "adjT": 83.93425925925925
    },
    {
      "teamId": "85",
      "team": "West Ala.",
      "conference": "gulf-south",
      "games": 28,
      "adjO": 118.46135164672074,
      "adjD": 97.17804696487785,
      "adjEM": 21.283304681842893,
      "adjT": 66.17589285714286
    },
    {
      "teamId": "700",
      "team": "Cal St. East Bay",
      "conference": "ccaa",
      "games": 27,
      "adjO": 111.05835179909253,
      "adjD": 90.65735770810642,
      "adjEM": 20.400994090986117,
      "adjT": 70.2
    },
    {
      "teamId": "1732",
      "team": "Palm Beach Atl.",
      "conference": "sunshine-state",
      "games": 27,
      "adjO": 116.84229057163695,
      "adjD": 96.5677865290943,
      "adjEM": 20.274504042542645,
      "adjT": 73.6351851851852
    },
    {
      "teamId": "16400",
      "team": "Black Hills St.",
      "conference": "rmac",
      "games": 27,
      "adjO": 115.79269536829217,
      "adjD": 95.56625285026603,
      "adjEM": 20.226442518026147,
      "adjT": 72.60740740740741
    },
    {
      "teamId": "515",
      "team": "DBU",
      "conference": "lone-star",
      "games": 27,
      "adjO": 110.31110567813703,
      "adjD": 90.62771436610758,
      "adjEM": 19.683391312029443,
      "adjT": 75.74537037037037
    },
    {
      "teamId": "2586",
      "team": "Rockhurst",
      "conference": "glvc",
      "games": 27,
      "adjO": 118.60626299540043,
      "adjD": 99.3829492507241,
      "adjEM": 19.223313744676332,
      "adjT": 73.47685185185185
    },
    {
      "teamId": "2570",
      "team": "Harding",
      "conference": "gac",
      "games": 27,
      "adjO": 114.79984055577701,
      "adjD": 97.12986643932936,
      "adjEM": 17.669974116447648,
      "adjT": 65.04074074074073
    },
    {
      "teamId": "16451",
      "team": "Point Loma",
      "conference": "pacwest",
      "games": 27,
      "adjO": 116.38862139864143,
      "adjD": 98.87275631374294,
      "adjEM": 17.515865084898493,
      "adjT": 71.15370370370371
    },
    {
      "teamId": "1926",
      "team": "Ouachita Baptist",
      "conference": "gac",
      "games": 27,
      "adjO": 110.25467782634475,
      "adjD": 92.86257168520694,
      "adjEM": 17.392106141137802,
      "adjT": 67.15092592592593
    },
    {
      "teamId": "879",
      "team": "Lander",
      "conference": "peach-belt",
      "games": 26,
      "adjO": 115.0408925960028,
      "adjD": 97.90922998470168,
      "adjEM": 17.131662611301124,
      "adjT": 71.01153846153846
    },
    {
      "teamId": "2684",
      "team": "Virginia Union",
      "conference": "ciaa",
      "games": 29,
      "adjO": 105.28616801038974,
      "adjD": 88.48836617280179,
      "adjEM": 16.797801837587954,
      "adjT": 67.04224137931034
    },
    {
      "teamId": "18517",
      "team": "Lubbock Christian",
      "conference": "lone-star",
      "games": 27,
      "adjO": 117.40918158255418,
      "adjD": 100.6959547629404,
      "adjEM": 16.71322681961378,
      "adjT": 68.23240740740741
    },
    {
      "teamId": "1508",
      "team": "Indiana (PA)",
      "conference": "psac",
      "games": 25,
      "adjO": 119.44925943150271,
      "adjD": 102.92997941400412,
      "adjEM": 16.519280017498588,
      "adjT": 70.959
    },
    {
      "teamId": "712",
      "team": "Central Mo.",
      "conference": "mid-america-intercollegiate",
      "games": 27,
      "adjO": 115.6485839753872,
      "adjD": 99.56858904798453,
      "adjEM": 16.079994927402666,
      "adjT": 70.42407407407407
    },
    {
      "teamId": "2365",
      "team": "West Chester",
      "conference": "psac",
      "games": 27,
      "adjO": 113.73731159643188,
      "adjD": 97.90399585487116,
      "adjEM": 15.833315741560725,
      "adjT": 75.25462962962963
    },
    {
      "teamId": "1431",
      "team": "West Florida",
      "conference": "gulf-south",
      "games": 30,
      "adjO": 117.8226734579929,
      "adjD": 102.07112330382144,
      "adjEM": 15.751550154171468,
      "adjT": 73.1325
    },
    {
      "teamId": "52017",
      "team": "Ohio Dominican",
      "conference": "g-mac",
      "games": 27,
      "adjO": 112.74902526304547,
      "adjD": 97.0593302323116,
      "adjEM": 15.689695030733873,
      "adjT": 69.34444444444445
    },
    {
      "teamId": "2146",
      "team": "Grand Valley St.",
      "conference": "gliac",
      "games": 28,
      "adjO": 111.65135962542769,
      "adjD": 96.62454827382936,
      "adjEM": 15.026811351598326,
      "adjT": 69.4125
    },
    {
      "teamId": "261808",
      "team": "McKendree",
      "conference": "glvc",
      "games": 27,
      "adjO": 109.83372394569332,
      "adjD": 94.91450512416785,
      "adjEM": 14.919218821525476,
      "adjT": 66.76759259259259
    },
    {
      "teamId": "2068",
      "team": "CSU Pueblo",
      "conference": "rmac",
      "games": 27,
      "adjO": 109.65846595101847,
      "adjD": 94.90632800285267,
      "adjEM": 14.752137948165796,
      "adjT": 66.50277777777778
    },
    {
      "teamId": "179",
      "team": "Montevallo",
      "conference": "gulf-south",
      "games": 28,
      "adjO": 111.49509371137401,
      "adjD": 96.93506753878154,
      "adjEM": 14.560026172592472,
      "adjT": 70.79107142857143
    },
    {
      "teamId": "2371",
      "team": "Felician",
      "conference": "cacc",
      "games": 26,
      "adjO": 109.83429949212538,
      "adjD": 95.27691445457788,
      "adjEM": 14.557385037547505,
      "adjT": 74.97307692307692
    },
    {
      "teamId": "734",
      "team": "Eastern N.M.",
      "conference": "lone-star",
      "games": 27,
      "adjO": 115.14711686592058,
      "adjD": 100.74081669272769,
      "adjEM": 14.40630017319289,
      "adjT": 72.72500000000001
    },
    {
      "teamId": "1314",
      "team": "St. Cloud St.",
      "conference": "nsic",
      "games": 28,
      "adjO": 107.9619403833761,
      "adjD": 93.66877791516313,
      "adjEM": 14.29316246821297,
      "adjT": 70.65982142857142
    },
    {
      "teamId": "53228",
      "team": "Okla. Baptist",
      "conference": "gac",
      "games": 27,
      "adjO": 112.92268076167242,
      "adjD": 98.65917129523784,
      "adjEM": 14.263509466434584,
      "adjT": 68.31944444444444
    },
    {
      "teamId": "1585",
      "team": "Charleston (WV)",
      "conference": "mec",
      "games": 26,
      "adjO": 119.7521446447451,
      "adjD": 105.62835259267167,
      "adjEM": 14.123792052073426,
      "adjT": 71.84711538461539
    },
    {
      "teamId": "424",
      "team": "Lake Superior St.",
      "conference": "gliac",
      "games": 28,
      "adjO": 117.42026792904028,
      "adjD": 103.41894880081645,
      "adjEM": 14.001319128223827,
      "adjT": 73.18035714285715
    },
    {
      "teamId": "1242",
      "team": "St. Edward's",
      "conference": "lone-star",
      "games": 28,
      "adjO": 114.72494123207422,
      "adjD": 100.87125119626145,
      "adjEM": 13.853690035812761,
      "adjT": 71.78660714285715
    },
    {
      "teamId": "1166",
      "team": "Millersville",
      "conference": "psac",
      "games": 28,
      "adjO": 110.78823543715879,
      "adjD": 97.03752149795315,
      "adjEM": 13.750713939205639,
      "adjT": 73.43482142857144
    },
    {
      "teamId": "2194",
      "team": "Michigan Tech",
      "conference": "gliac",
      "games": 27,
      "adjO": 110.1185956289434,
      "adjD": 96.62340519137703,
      "adjEM": 13.495190437566364,
      "adjT": 67.06574074074075
    },
    {
      "teamId": "156",
      "team": "Catawba",
      "conference": "sac",
      "games": 27,
      "adjO": 110.91749374952649,
      "adjD": 97.6872232723951,
      "adjEM": 13.230270477131384,
      "adjT": 73.32777777777777
    },
    {
      "teamId": "16455",
      "team": "UVA Wise",
      "conference": "sac",
      "games": 27,
      "adjO": 112.32145973028891,
      "adjD": 99.09954977488744,
      "adjEM": 13.221909955401472,
      "adjT": 74.29074074074073
    },
    {
      "teamId": "817",
      "team": "UAH",
      "conference": "gulf-south",
      "games": 28,
      "adjO": 115.15846123181184,
      "adjD": 102.05149936435924,
      "adjEM": 13.106961867452597,
      "adjT": 71.67142857142856
    },
    {
      "teamId": "2407",
      "team": "Fort Hays St.",
      "conference": "mid-america-intercollegiate",
      "games": 28,
      "adjO": 105.81447903650334,
      "adjD": 92.74357661454435,
      "adjEM": 13.07090242195899,
      "adjT": 67.16607142857143
    },
    {
      "teamId": "2619",
      "team": "UNC Pembroke",
      "conference": "conference-carolinas",
      "games": 28,
      "adjO": 113.85189605047673,
      "adjD": 100.84882780921585,
      "adjEM": 13.003068241260877,
      "adjT": 70.32946428571428
    },
    {
      "teamId": "2520",
      "team": "Missouri S&T",
      "conference": "glvc",
      "games": 26,
      "adjO": 109.130993937167,
      "adjD": 96.34180029202457,
      "adjEM": 12.789193645142433,
      "adjT": 73.27115384615385
    },
    {
      "teamId": "2066",
      "team": "Ark.-Fort Smith",
      "conference": "mid-america-intercollegiate",
      "games": 27,
      "adjO": 110.05500215446227,
      "adjD": 97.31879377382626,
      "adjEM": 12.736208380636015,
      "adjT": 73.06111111111112
    },
    {
      "teamId": "809",
      "team": "Mo.-St. Louis",
      "conference": "glvc",
      "games": 27,
      "adjO": 109.2816197097207,
      "adjD": 96.82593166655435,
      "adjEM": 12.455688043166347,
      "adjT": 68.325
    },
    {
      "teamId": "1562",
      "team": "Bentley",
      "conference": "ne10",
      "games": 27,
      "adjO": 116.0583039111978,
      "adjD": 104.03908346521709,
      "adjEM": 12.019220445980707,
      "adjT": 67.39907407407408
    },
    {
      "teamId": "1470",
      "team": "East Stroudsburg",
      "conference": "psac",
      "games": 27,
      "adjO": 113.06887779138792,
      "adjD": 101.13971939894924,
      "adjEM": 11.92915839243868,
      "adjT": 78.6148148148148
    },
    {
      "teamId": "1441",
      "team": "California (PA)",
      "conference": "psac",
      "games": 26,
      "adjO": 111.53227062671998,
      "adjD": 99.653836749926,
      "adjEM": 11.878433876793977,
      "adjT": 74.07307692307693
    },
    {
      "teamId": "2522",
      "team": "Alas. Anchorage",
      "conference": "great-northwest",
      "games": 25,
      "adjO": 108.16624414227549,
      "adjD": 97.23628109567191,
      "adjEM": 10.929963046603575,
      "adjT": 65.085
    },
    {
      "teamId": "16543",
      "team": "Rogers St.",
      "conference": "mid-america-intercollegiate",
      "games": 27,
      "adjO": 110.57031002010369,
      "adjD": 99.65971141417606,
      "adjEM": 10.910598605927632,
      "adjT": 70.00740740740741
    },
    {
      "teamId": "18501",
      "team": "Young Harris",
      "conference": "conference-carolinas",
      "games": 28,
      "adjO": 114.67746961670302,
      "adjD": 103.9159975293391,
      "adjEM": 10.761472087363927,
      "adjT": 71.62946428571429
    },
    {
      "teamId": "1605",
      "team": "St. Mary's (TX)",
      "conference": "lone-star",
      "games": 27,
      "adjO": 111.06741573033707,
      "adjD": 100.78883150785995,
      "adjEM": 10.278584222477122,
      "adjT": 65.92592592592592
    },
    {
      "teamId": "2087",
      "team": "Cal St. Dom. Hills",
      "conference": "ccaa",
      "games": 28,
      "adjO": 114.20565839484233,
      "adjD": 104.04982813428785,
      "adjEM": 10.155830260554481,
      "adjT": 68.82946428571428
    },
    {
      "teamId": "2400",
      "team": "Lake Erie",
      "conference": "g-mac",
      "games": 27,
      "adjO": 110.91085539997228,
      "adjD": 100.86791711449341,
      "adjEM": 10.042938285478868,
      "adjT": 80.14444444444445
    },
    {
      "teamId": "2059",
      "team": "North Georgia",
      "conference": "peach-belt",
      "games": 25,
      "adjO": 110.97325215685143,
      "adjD": 100.94330169908818,
      "adjEM": 10.029950457763249,
      "adjT": 69.314
    },
    {
      "teamId": "2196",
      "team": "Minn. Duluth",
      "conference": "nsic",
      "games": 29,
      "adjO": 112.3150759487408,
      "adjD": 102.40637763889573,
      "adjEM": 9.908698309845065,
      "adjT": 69.69310344827586
    },
    {
      "teamId": "318",
      "team": "Ill. Springfield",
      "conference": "glvc",
      "games": 27,
      "adjO": 114.84730344379469,
      "adjD": 105.32443445652322,
      "adjEM": 9.522868987271465,
      "adjT": 68.39999999999999
    },
    {
      "teamId": "525",
      "team": "Glenville St.",
      "conference": "mec",
      "games": 27,
      "adjO": 113.83862618335677,
      "adjD": 104.47409363066333,
      "adjEM": 9.364532552693433,
      "adjT": 78.34351851851852
    },
    {
      "teamId": "261795",
      "team": "Southern Nazarene",
      "conference": "gac",
      "games": 27,
      "adjO": 107.39033210943323,
      "adjD": 98.08917197452229,
      "adjEM": 9.301160134910944,
      "adjT": 67.07962962962964
    },
    {
      "teamId": "1251",
      "team": "Western N.M.",
      "conference": "lone-star",
      "games": 27,
      "adjO": 107.96512449118482,
      "adjD": 98.92061058951268,
      "adjEM": 9.044513901672147,
      "adjT": 72.10833333333333
    },
    {
      "teamId": "693",
      "team": "Colorado Mesa",
      "conference": "rmac",
      "games": 27,
      "adjO": 118.06350018169829,
      "adjD": 109.13875983564733,
      "adjEM": 8.924740346050953,
      "adjT": 68.79537037037036
    },
    {
      "teamId": "294",
      "team": "Tuskegee",
      "conference": "siac",
      "games": 26,
      "adjO": 102.70332056924043,
      "adjD": 93.82147778772251,
      "adjEM": 8.881842781517918,
      "adjT": 67.29615384615384
    },
    {
      "teamId": "680",
      "team": "Southwest Minn. St.",
      "conference": "nsic",
      "games": 27,
      "adjO": 111.78732036713906,
      "adjD": 102.96389743298984,
      "adjEM": 8.823422934149221,
      "adjT": 65.26944444444445
    },
    {
      "teamId": "2456",
      "team": "Fla. Southern",
      "conference": "sunshine-state",
      "games": 27,
      "adjO": 114.5403531935963,
      "adjD": 105.82010582010581,
      "adjEM": 8.720247373490494,
      "adjT": 78.5425925925926
    },
    {
      "teamId": "1417",
      "team": "Goldey-Beacom",
      "conference": "cacc",
      "games": 27,
      "adjO": 112.96571913553673,
      "adjD": 104.41796338811756,
      "adjEM": 8.547755747419174,
      "adjT": 75.27685185185184
    },
    {
      "teamId": "1222",
      "team": "Findlay",
      "conference": "g-mac",
      "games": 27,
      "adjO": 115.70961574045519,
      "adjD": 107.37790948941162,
      "adjEM": 8.33170625104357,
      "adjT": 75.06018518518519
    },
    {
      "teamId": "2634",
      "team": "Saint Anselm",
      "conference": "ne10",
      "games": 28,
      "adjO": 116.2630105339812,
      "adjD": 107.95732971465188,
      "adjEM": 8.305680819329325,
      "adjT": 71.11339285714286
    },
    {
      "teamId": "1912",
      "team": "Ga. Southwestern",
      "conference": "peach-belt",
      "games": 27,
      "adjO": 110.81034687652674,
      "adjD": 102.51655629139074,
      "adjEM": 8.293790585135994,
      "adjT": 70.12314814814815
    },
    {
      "teamId": "1866",
      "team": "Augustana (SD)",
      "conference": "nsic",
      "games": 27,
      "adjO": 116.57748454465167,
      "adjD": 108.42437736239839,
      "adjEM": 8.15310718225328,
      "adjT": 71.2925925925926
    },
    {
      "teamId": "1853",
      "team": "Adelphi",
      "conference": "ne10",
      "games": 28,
      "adjO": 105.9311499862614,
      "adjD": 98.05019732471965,
      "adjEM": 7.880952661541755,
      "adjT": 68.23839285714286
    },
    {
      "teamId": "341",
      "team": "East Central",
      "conference": "gac",
      "games": 27,
      "adjO": 109.16940506799027,
      "adjD": 101.33631809557609,
      "adjEM": 7.833086972414179,
      "adjT": 67.34351851851852
    },
    {
      "teamId": "1373",
      "team": "West Tex. A&M",
      "conference": "lone-star",
      "games": 27,
      "adjO": 111.45706640720019,
      "adjD": 103.71726789965207,
      "adjEM": 7.739798507548116,
      "adjT": 76.12962962962963
    },
    {
      "teamId": "53229",
      "team": "Westminster (UT)",
      "conference": "rmac",
      "games": 27,
      "adjO": 110.72042707183738,
      "adjD": 103.02299941027154,
      "adjEM": 7.69742766156584,
      "adjT": 72.15370370370371
    },
    {
      "teamId": "1427",
      "team": "Mo. Southern St.",
      "conference": "mid-america-intercollegiate",
      "games": 27,
      "adjO": 112.68788518779256,
      "adjD": 105.01288387088744,
      "adjEM": 7.675001316905124,
      "adjT": 74.96944444444445
    },
    {
      "teamId": "1618",
      "team": "Morehouse",
      "conference": "siac",
      "games": 29,
      "adjO": 104.89229156253428,
      "adjD": 97.25804677090082,
      "adjEM": 7.6342447916334635,
      "adjT": 70.71293103448276
    },
    {
      "teamId": "2584",
      "team": "Pittsburg St.",
      "conference": "mid-america-intercollegiate",
      "games": 26,
      "adjO": 110.50028245084667,
      "adjD": 102.9304683528652,
      "adjEM": 7.569814097981464,
      "adjT": 69.7875
    },
    {
      "teamId": "1553",
      "team": "Ashland",
      "conference": "g-mac",
      "games": 27,
      "adjO": 112.27958781433125,
      "adjD": 104.71594998800353,
      "adjEM": 7.563637826327721,
      "adjT": 69.99722222222222
    },
    {
      "teamId": "2564",
      "team": "Central Okla.",
      "conference": "mid-america-intercollegiate",
      "games": 27,
      "adjO": 105.79027212802234,
      "adjD": 98.25496203543359,
      "adjEM": 7.535310092588745,
      "adjT": 68.96944444444445
    },
    {
      "teamId": "2563",
      "team": "Carson-Newman",
      "conference": "sac",
      "games": 27,
      "adjO": 107.60082730093072,
      "adjD": 100.22005173145969,
      "adjEM": 7.380775569471027,
      "adjT": 71.62962962962963
    },
    {
      "teamId": "2029",
      "team": "Virginia St.",
      "conference": "ciaa",
      "games": 30,
      "adjO": 98.36736550093228,
      "adjD": 90.9959854712292,
      "adjEM": 7.371380029703076,
      "adjT": 73.29666666666667
    },
    {
      "teamId": "1388732",
      "team": "USC Beaufort",
      "conference": "peach-belt",
      "games": 27,
      "adjO": 110.7242094896416,
      "adjD": 103.48968717572025,
      "adjEM": 7.234522313921346,
      "adjT": 78.975
    },
    {
      "teamId": "1428",
      "team": "Missouri Western",
      "conference": "mid-america-intercollegiate",
      "games": 27,
      "adjO": 114.52549701916435,
      "adjD": 107.30619931588454,
      "adjEM": 7.219297703279807,
      "adjT": 72.37592592592593
    },
    {
      "teamId": "366",
      "team": "Columbus St.",
      "conference": "peach-belt",
      "games": 27,
      "adjO": 109.2893300900664,
      "adjD": 102.14181083970071,
      "adjEM": 7.14751925036569,
      "adjT": 70.42129629629629
    },
    {
      "teamId": "445",
      "team": "Miles",
      "conference": "siac",
      "games": 26,
      "adjO": 105.33618225712462,
      "adjD": 98.27353542660786,
      "adjEM": 7.062646830516755,
      "adjT": 69.30192307692307
    },
    {
      "teamId": "2078",
      "team": "Shepherd",
      "conference": "psac",
      "games": 27,
      "adjO": 109.17966101694915,
      "adjD": 102.11847254081769,
      "adjEM": 7.061188476131463,
      "adjT": 68.28703703703704
    },
    {
      "teamId": "378",
      "team": "Mont. St. Billings",
      "conference": "great-northwest",
      "games": 27,
      "adjO": 112.9234318601853,
      "adjD": 105.91923472485534,
      "adjEM": 7.00419713532996,
      "adjT": 74.64907407407408
    },
    {
      "teamId": "386",
      "team": "Fayetteville St.",
      "conference": "ciaa",
      "games": 28,
      "adjO": 106.98750185668513,
      "adjD": 100.03320159796078,
      "adjEM": 6.954300258724345,
      "adjT": 84.15535714285714
    },
    {
      "teamId": "1236",
      "team": "Lincoln Memorial",
      "conference": "sac",
      "games": 27,
      "adjO": 108.97779137662866,
      "adjD": 102.03643074744973,
      "adjEM": 6.941360629178931,
      "adjT": 72.62777777777778
    },
    {
      "teamId": "1149",
      "team": "Minnesota St.",
      "conference": "nsic",
      "games": 29,
      "adjO": 113.34556605051537,
      "adjD": 106.40704135319861,
      "adjEM": 6.938524697316765,
      "adjT": 70.00258620689655
    },
    {
      "teamId": "1247",
      "team": "Thomas More",
      "conference": "g-mac",
      "games": 26,
      "adjO": 115.24419746931953,
      "adjD": 108.34505738615327,
      "adjEM": 6.899140083166259,
      "adjT": 65.5798076923077
    },
    {
      "teamId": "567",
      "team": "Northwood",
      "conference": "g-mac",
      "games": 27,
      "adjO": 108.28617072657248,
      "adjD": 101.4446068835642,
      "adjEM": 6.841563843008274,
      "adjT": 74.76759259259259
    },
    {
      "teamId": "942",
      "team": "Rollins",
      "conference": "sunshine-state",
      "games": 28,
      "adjO": 113.80573764362802,
      "adjD": 107.0274182880106,
      "adjEM": 6.778319355617427,
      "adjT": 71.64464285714286
    },
    {
      "teamId": "620",
      "team": "Staten Island",
      "conference": "ecc",
      "games": 27,
      "adjO": 111.23560683719933,
      "adjD": 104.6303585486295,
      "adjEM": 6.605248288569825,
      "adjT": 77.67962962962963
    },
    {
      "teamId": "1388510",
      "team": "Westmont",
      "conference": "pacwest",
      "games": 27,
      "adjO": 112.27934259310499,
      "adjD": 105.89943979528323,
      "adjEM": 6.379902797821757,
      "adjT": 66.92962962962963
    },
    {
      "teamId": "2713",
      "team": "Flagler",
      "conference": "peach-belt",
      "games": 27,
      "adjO": 102.59115184281664,
      "adjD": 96.27904514899699,
      "adjEM": 6.312106693819658,
      "adjT": 70.2175925925926
    },
    {
      "teamId": "16469",
      "team": "Dominican (CA)",
      "conference": "pacwest",
      "games": 28,
      "adjO": 105.88791676519271,
      "adjD": 99.73122082331307,
      "adjEM": 6.156695941879647,
      "adjT": 75.51785714285714
    },
    {
      "teamId": "2678",
      "team": "Valdosta St.",
      "conference": "gulf-south",
      "games": 28,
      "adjO": 116.87248337202911,
      "adjD": 110.74435836982148,
      "adjEM": 6.128125002207625,
      "adjT": 79.60446428571429
    },
    {
      "teamId": "1818",
      "team": "UIndy",
      "conference": "glvc",
      "games": 27,
      "adjO": 112.83890479886519,
      "adjD": 106.75975028529234,
      "adjEM": 6.0791545135728455,
      "adjT": 69.19074074074075
    },
    {
      "teamId": "18001",
      "team": "William Jewell",
      "conference": "glvc",
      "games": 27,
      "adjO": 106.07776519441299,
      "adjD": 100.00270131554068,
      "adjEM": 6.075063878872314,
      "adjT": 68.67777777777778
    },
    {
      "teamId": "1046",
      "team": "Wheeling",
      "conference": "mec",
      "games": 26,
      "adjO": 112.11166141377757,
      "adjD": 106.20219840546983,
      "adjEM": 5.909463008307739,
      "adjT": 76.88076923076923
    },
    {
      "teamId": "261802",
      "team": "Trevecca Nazarene",
      "conference": "gulf-south",
      "games": 28,
      "adjO": 110.68922143722007,
      "adjD": 104.87050546544845,
      "adjEM": 5.818715971771624,
      "adjT": 75.95267857142858
    },
    {
      "teamId": "1035",
      "team": "Chowan",
      "conference": "conference-carolinas",
      "games": 28,
      "adjO": 110.26729653770258,
      "adjD": 104.50920135359745,
      "adjEM": 5.75809518410513,
      "adjT": 74.65625
    },
    {
      "teamId": "313",
      "team": "UT Tyler",
      "conference": "lone-star",
      "games": 25,
      "adjO": 101.4289717007565,
      "adjD": 95.69858012735659,
      "adjEM": 5.730391573399913,
      "adjT": 71.38
    },
    {
      "teamId": "362",
      "team": "Clark Atlanta",
      "conference": "siac",
      "games": 28,
      "adjO": 98.77461923897405,
      "adjD": 93.23574200520706,
      "adjEM": 5.538877233766996,
      "adjT": 71.98928571428571
    },
    {
      "teamId": "1009",
      "team": "Cal St. Monterey Bay",
      "conference": "ccaa",
      "games": 27,
      "adjO": 113.05171433983709,
      "adjD": 107.55267177499779,
      "adjEM": 5.4990425648393,
      "adjT": 73.31944444444444
    },
    {
      "teamId": "1897",
      "team": "Central Wash.",
      "conference": "great-northwest",
      "games": 25,
      "adjO": 110.9322768354587,
      "adjD": 105.46702080566621,
      "adjEM": 5.465256029792485,
      "adjT": 72.693
    },
    {
      "teamId": "58649",
      "team": "Purdue Northwest",
      "conference": "gliac",
      "games": 26,
      "adjO": 112.06996409127765,
      "adjD": 106.70701246057006,
      "adjEM": 5.362951630707599,
      "adjT": 66.4076923076923
    },
    {
      "teamId": "2409",
      "team": "Concordia-St. Paul",
      "conference": "nsic",
      "games": 28,
      "adjO": 111.51699765590604,
      "adjD": 106.22939974245986,
      "adjEM": 5.287597913446177,
      "adjT": 75.03660714285715
    },
    {
      "teamId": "1713",
      "team": "Upper Iowa",
      "conference": "glvc",
      "games": 26,
      "adjO": 110.92943641101631,
      "adjD": 105.65069591430954,
      "adjEM": 5.278740496706774,
      "adjT": 75.27307692307691
    },
    {
      "teamId": "1902",
      "team": "Drury",
      "conference": "glvc",
      "games": 27,
      "adjO": 112.55267101269229,
      "adjD": 107.4646733565431,
      "adjEM": 5.087997656149184,
      "adjT": 72.29537037037036
    },
    {
      "teamId": "265",
      "team": "Shaw",
      "conference": "ciaa",
      "games": 27,
      "adjO": 107.51476245313994,
      "adjD": 102.43038472891864,
      "adjEM": 5.084377724221298,
      "adjT": 75.57962962962964
    },
    {
      "teamId": "834",
      "team": "Barry",
      "conference": "sunshine-state",
      "games": 27,
      "adjO": 108.9760849876386,
      "adjD": 103.93923852785308,
      "adjEM": 5.036846459785522,
      "adjT": 75.65370370370371
    },
    {
      "teamId": "534",
      "team": "Northwest Nazarene",
      "conference": "great-northwest",
      "games": 26,
      "adjO": 110.72626007924853,
      "adjD": 105.74030690749802,
      "adjEM": 4.985953171750509,
      "adjT": 69.40192307692308
    },
    {
      "teamId": "1380",
      "team": "Lynn",
      "conference": "sunshine-state",
      "games": 26,
      "adjO": 114.0349751735287,
      "adjD": 109.15731269713571,
      "adjEM": 4.877662476392985,
      "adjT": 74.94326923076923
    },
    {
      "teamId": "1342",
      "team": "Tampa",
      "conference": "sunshine-state",
      "games": 26,
      "adjO": 109.66860266484456,
      "adjD": 104.841361671031,
      "adjEM": 4.827240993813561,
      "adjT": 78.80384615384615
    },
    {
      "teamId": "1012",
      "team": "Seton Hill",
      "conference": "psac",
      "games": 27,
      "adjO": 109.03944983738425,
      "adjD": 104.66136756851634,
      "adjEM": 4.378082268867914,
      "adjT": 74.59074074074074
    },
    {
      "teamId": "261803",
      "team": "Lee",
      "conference": "gulf-south",
      "games": 26,
      "adjO": 111.08581834737082,
      "adjD": 106.95579743904678,
      "adjEM": 4.130020908324042,
      "adjT": 67.58461538461539
    },
    {
      "teamId": "1453",
      "team": "Colo. Sch. of Mines",
      "conference": "rmac",
      "games": 28,
      "adjO": 111.6703645007924,
      "adjD": 107.58196721311475,
      "adjEM": 4.088397287677651,
      "adjT": 70.42410714285714
    },
    {
      "teamId": "1752",
      "team": "North Greenville",
      "conference": "conference-carolinas",
      "games": 29,
      "adjO": 103.74279390248478,
      "adjD": 99.70965580564311,
      "adjEM": 4.033138096841668,
      "adjT": 68.93706896551724
    },
    {
      "teamId": "2646",
      "team": "Seattle Pacific",
      "conference": "great-northwest",
      "games": 24,
      "adjO": 109.83521473984688,
      "adjD": 105.94264953937977,
      "adjEM": 3.8925652004671036,
      "adjT": 64.22500000000001
    },
    {
      "teamId": "388",
      "team": "Ferrum",
      "conference": "conference-carolinas",
      "games": 25,
      "adjO": 114.10344296926371,
      "adjD": 110.38815346645725,
      "adjEM": 3.7152895028064563,
      "adjT": 71.479
    },
    {
      "teamId": "2528",
      "team": "Assumption",
      "conference": "ne10",
      "games": 27,
      "adjO": 105.66736965293609,
      "adjD": 102.29096745950679,
      "adjEM": 3.3764021934293,
      "adjT": 75.95462962962964
    },
    {
      "teamId": "53222",
      "team": "Embry-Riddle (FL)",
      "conference": "sunshine-state",
      "games": 26,
      "adjO": 112.72472332114778,
      "adjD": 109.4221864304409,
      "adjEM": 3.3025368907068753,
      "adjT": 76.80384615384615
    },
    {
      "teamId": "673",
      "team": "Southwest Baptist",
      "conference": "glvc",
      "games": 27,
      "adjO": 107.8657942363915,
      "adjD": 104.60827568929282,
      "adjEM": 3.2575185470986696,
      "adjT": 66.50925925925925
    },
    {
      "teamId": "1655",
      "team": "Pace",
      "conference": "ne10",
      "games": 26,
      "adjO": 99.25720835380105,
      "adjD": 96.08046147019672,
      "adjEM": 3.1767468836043236,
      "adjT": 64.5951923076923
    },
    {
      "teamId": "2067",
      "team": "Hawaii Pacific",
      "conference": "pacwest",
      "games": 27,
      "adjO": 111.13342706032002,
      "adjD": 108.121108468507,
      "adjEM": 3.0123185918130133,
      "adjT": 69.15277777777777
    },
    {
      "teamId": "58647",
      "team": "Biola",
      "conference": "pacwest",
      "games": 27,
      "adjO": 104.68369750523809,
      "adjD": 101.70104024160452,
      "adjEM": 2.9826572636335698,
      "adjT": 71.14907407407408
    },
    {
      "teamId": "261804",
      "team": "Cedarville",
      "conference": "g-mac",
      "games": 27,
      "adjO": 111.30824540106453,
      "adjD": 108.39244440902208,
      "adjEM": 2.915800992042449,
      "adjT": 69.41018518518518
    },
    {
      "teamId": "2316",
      "team": "Saginaw Valley",
      "conference": "gliac",
      "games": 27,
      "adjO": 107.95783620989228,
      "adjD": 105.0617858435448,
      "adjEM": 2.896050366347481,
      "adjT": 71.94166666666666
    },
    {
      "teamId": "261816",
      "team": "Emmanuel (GA)",
      "conference": "conference-carolinas",
      "games": 28,
      "adjO": 112.04242431858451,
      "adjD": 109.1943979828744,
      "adjEM": 2.8480263357101023,
      "adjT": 71.05089285714286
    },
    {
      "teamId": "1388735",
      "team": "Jessup",
      "conference": "pacwest",
      "games": 27,
      "adjO": 104.75694702659825,
      "adjD": 101.97736599925382,
      "adjEM": 2.7795810273444346,
      "adjT": 74.70555555555555
    },
    {
      "teamId": "2297",
      "team": "Jefferson",
      "conference": "cacc",
      "games": 27,
      "adjO": 109.1850460648207,
      "adjD": 106.40759908953345,
      "adjEM": 2.7774469752872477,
      "adjT": 72.96481481481482
    },
    {
      "teamId": "1581",
      "team": "Adams St.",
      "conference": "rmac",
      "games": 27,
      "adjO": 106.55700664286682,
      "adjD": 103.96889973781755,
      "adjEM": 2.5881069050492727,
      "adjT": 81.95925925925927
    },
    {
      "teamId": "1049",
      "team": "Barton",
      "conference": "conference-carolinas",
      "games": 28,
      "adjO": 112.13432449424904,
      "adjD": 109.55578128484007,
      "adjEM": 2.578543209408977,
      "adjT": 72.42589285714286
    },
    {
      "teamId": "1934",
      "team": "St. Thomas Aquinas",
      "conference": "ecc",
      "games": 27,
      "adjO": 107.17073580804382,
      "adjD": 104.63533069054019,
      "adjEM": 2.535405117503629,
      "adjT": 77.10092592592592
    },
    {
      "teamId": "2214",
      "team": "Augusta",
      "conference": "peach-belt",
      "games": 28,
      "adjO": 108.30234194391397,
      "adjD": 106.00582504770513,
      "adjEM": 2.2965168962088427,
      "adjT": 71.06428571428572
    },
    {
      "teamId": "1388724",
      "team": "Vanguard",
      "conference": "pacwest",
      "games": 27,
      "adjO": 103.79770811629889,
      "adjD": 101.68670809458477,
      "adjEM": 2.111000021714119,
      "adjT": 68.43796296296297
    },
    {
      "teamId": "1048",
      "team": "Northeastern St.",
      "conference": "mid-america-intercollegiate",
      "games": 28,
      "adjO": 108.25675135732249,
      "adjD": 106.19261482897313,
      "adjEM": 2.0641365283493514,
      "adjT": 75.97678571428571
    },
    {
      "teamId": "469",
      "team": "Benedict",
      "conference": "siac",
      "games": 24,
      "adjO": 94.629554592775,
      "adjD": 92.59087106070466,
      "adjEM": 2.038683532070337,
      "adjT": 66.83958333333334
    },
    {
      "teamId": "48",
      "team": "Frostburg St.",
      "conference": "mec",
      "games": 27,
      "adjO": 117.53159991959609,
      "adjD": 115.53322113447271,
      "adjEM": 1.9983787851233785,
      "adjT": 78.30833333333332
    },
    {
      "teamId": "1053",
      "team": "Cal Poly Pomona",
      "conference": "ccaa",
      "games": 27,
      "adjO": 103.20125059471216,
      "adjD": 101.32034078520573,
      "adjEM": 1.8809098095064343,
      "adjT": 68.11574074074075
    },
    {
      "teamId": "427",
      "team": "Lincoln (MO)",
      "conference": "glvc",
      "games": 28,
      "adjO": 105.68052044705067,
      "adjD": 103.86597938144331,
      "adjEM": 1.814541065607358,
      "adjT": 69.58303571428571
    },
    {
      "teamId": "1909",
      "team": "Fort Lewis",
      "conference": "rmac",
      "games": 26,
      "adjO": 104.94464944649447,
      "adjD": 103.15922025654002,
      "adjEM": 1.785429189954442,
      "adjT": 78.17307692307692
    },
    {
      "teamId": "2262",
      "team": "Wayne St. (NE)",
      "conference": "nsic",
      "games": 29,
      "adjO": 109.1051421302412,
      "adjD": 107.33223173107751,
      "adjEM": 1.7729103991636919,
      "adjT": 70.4793103448276
    },
    {
      "teamId": "53225",
      "team": "Cal St. San Marcos",
      "conference": "ccaa",
      "games": 26,
      "adjO": 107.66638584667227,
      "adjD": 105.97641188478113,
      "adjEM": 1.6899739618911411,
      "adjT": 68.48076923076923
    },
    {
      "teamId": "2490",
      "team": "LeMoyne-Owen",
      "conference": "siac",
      "games": 25,
      "adjO": 96.408206454647,
      "adjD": 94.73418997228521,
      "adjEM": 1.6740164823617931,
      "adjT": 68.044
    },
    {
      "teamId": "1862",
      "team": "Angelo St.",
      "conference": "lone-star",
      "games": 28,
      "adjO": 99.69595344042384,
      "adjD": 98.04302999649846,
      "adjEM": 1.6529234439253742,
      "adjT": 68.42232142857144
    },
    {
      "teamId": "1266",
      "team": "Southern N.H.",
      "conference": "ne10",
      "games": 27,
      "adjO": 108.06251812023933,
      "adjD": 106.420903917504,
      "adjEM": 1.641614202735326,
      "adjT": 70.2611111111111
    },
    {
      "teamId": "16416",
      "team": "Malone",
      "conference": "g-mac",
      "games": 27,
      "adjO": 105.01096871031059,
      "adjD": 103.50998729938806,
      "adjEM": 1.5009814109225346,
      "adjT": 64.15555555555555
    },
    {
      "teamId": "1388154",
      "team": "Edward Waters",
      "conference": "siac",
      "games": 28,
      "adjO": 96.28073279516384,
      "adjD": 94.81401298956898,
      "adjEM": 1.4667198055948631,
      "adjT": 72.66696428571429
    },
    {
      "teamId": "1993",
      "team": "Saint Michael's",
      "conference": "ne10",
      "games": 28,
      "adjO": 104.34518844316372,
      "adjD": 103.13613415754952,
      "adjEM": 1.2090542856142008,
      "adjT": 70.64464285714286
    },
    {
      "teamId": "2330",
      "team": "Slippery Rock",
      "conference": "psac",
      "games": 27,
      "adjO": 104.58162407947414,
      "adjD": 103.38978884491532,
      "adjEM": 1.1918352345588232,
      "adjT": 74.93703703703703
    },
    {
      "teamId": "379",
      "team": "Edinboro",
      "conference": "psac",
      "games": 26,
      "adjO": 108.88754127080385,
      "adjD": 107.75186529677308,
      "adjEM": 1.1356759740307751,
      "adjT": 71.35096153846153
    },
    {
      "teamId": "56150",
      "team": "Sioux Falls",
      "conference": "nsic",
      "games": 29,
      "adjO": 112.61129268567565,
      "adjD": 111.49495360021677,
      "adjEM": 1.1163390854588755,
      "adjT": 76.49137931034483
    },
    {
      "teamId": "44",
      "team": "Eckerd",
      "conference": "sunshine-state",
      "games": 26,
      "adjO": 108.21341368382772,
      "adjD": 107.10916398506055,
      "adjEM": 1.1042496987671768,
      "adjT": 74.03461538461539
    },
    {
      "teamId": "2689",
      "team": "Wayne St. (MI)",
      "conference": "gliac",
      "games": 25,
      "adjO": 111.03836585046484,
      "adjD": 110.04848145473835,
      "adjEM": 0.9898843957264916,
      "adjT": 68.733
    },
    {
      "teamId": "193",
      "team": "Western Wash.",
      "conference": "great-northwest",
      "games": 25,
      "adjO": 111.80040276257282,
      "adjD": 110.87408454148945,
      "adjEM": 0.9263182210833634,
      "adjT": 73.98899999999999
    },
    {
      "teamId": "1484",
      "team": "Fort Valley St.",
      "conference": "siac",
      "games": 25,
      "adjO": 101.23614953729574,
      "adjD": 100.46678245766391,
      "adjEM": 0.7693670796318344,
      "adjT": 73.373
    },
    {
      "teamId": "1754",
      "team": "UCCS",
      "conference": "rmac",
      "games": 28,
      "adjO": 114.07295363313747,
      "adjD": 113.3102135659322,
      "adjEM": 0.7627400672052715,
      "adjT": 76.73660714285714
    },
    {
      "teamId": "544",
      "team": "Wingate",
      "conference": "sac",
      "games": 27,
      "adjO": 109.3183538504442,
      "adjD": 108.61846567108606,
      "adjEM": 0.6998881793581404,
      "adjT": 69.72500000000001
    },
    {
      "teamId": "423",
      "team": "Ky. Wesleyan",
      "conference": "g-mac",
      "games": 27,
      "adjO": 108.78638110928061,
      "adjD": 108.17288052506878,
      "adjEM": 0.6135005842118346,
      "adjT": 67.44444444444444
    },
    {
      "teamId": "1176",
      "team": "Alas. Fairbanks",
      "conference": "great-northwest",
      "games": 24,
      "adjO": 107.900703447474,
      "adjD": 107.44277004486369,
      "adjEM": 0.45793340261030835,
      "adjT": 71.67083333333333
    },
    {
      "teamId": "1424",
      "team": "Dominican (NY)",
      "conference": "cacc",
      "games": 27,
      "adjO": 106.5628582346198,
      "adjD": 106.23298500897558,
      "adjEM": 0.3298732256442207,
      "adjT": 77.54074074074073
    },
    {
      "teamId": "53226",
      "team": "CUI",
      "conference": "pacwest",
      "games": 27,
      "adjO": 101.14621641210104,
      "adjD": 100.88190131945483,
      "adjEM": 0.2643150926462141,
      "adjT": 68.98703703703704
    },
    {
      "teamId": "154",
      "team": "Bluefield St.",
      "conference": "ciaa",
      "games": 30,
      "adjO": 102.5875190258752,
      "adjD": 102.36139630390144,
      "adjEM": 0.22612272197375205,
      "adjT": 65.7
    },
    {
      "teamId": "480",
      "team": "Bridgeport",
      "conference": "cacc",
      "games": 26,
      "adjO": 103.87672677694029,
      "adjD": 103.6623773958427,
      "adjEM": 0.21434938109759116,
      "adjT": 74.75576923076923
    },
    {
      "teamId": "1060",
      "team": "Stanislaus St.",
      "conference": "ccaa",
      "games": 27,
      "adjO": 105.03483989914054,
      "adjD": 104.89481925250188,
      "adjEM": 0.14002064663866065,
      "adjT": 68.30185185185185
    },
    {
      "teamId": "950",
      "team": "Savannah St.",
      "conference": "siac",
      "games": 26,
      "adjO": 94.88457786929662,
      "adjD": 94.82115991922039,
      "adjEM": 0.06341795007622864,
      "adjT": 70.97692307692309
    },
    {
      "teamId": "1971",
      "team": "Pitt.-Johnstown",
      "conference": "psac",
      "games": 27,
      "adjO": 107.2485665102109,
      "adjD": 107.18605741933891,
      "adjEM": 0.0625090908719983,
      "adjT": 74.76574074074074
    },
    {
      "teamId": "58648",
      "team": "Davenport",
      "conference": "gliac",
      "games": 27,
      "adjO": 101.54184743425962,
      "adjD": 101.60059224465832,
      "adjEM": -0.05874481039869295,
      "adjT": 73.20462962962964
    },
    {
      "teamId": "681",
      "team": "Southwestern Okla.",
      "conference": "gac",
      "games": 27,
      "adjO": 103.2585004359198,
      "adjD": 103.46521145975443,
      "adjEM": -0.2067110238346288,
      "adjT": 67.97037037037038
    },
    {
      "teamId": "2411",
      "team": "USC Aiken",
      "conference": "peach-belt",
      "games": 27,
      "adjO": 106.35147554375575,
      "adjD": 106.56772564479142,
      "adjEM": -0.21625010103566922,
      "adjT": 72.54074074074073
    },
    {
      "teamId": "1388991",
      "team": "Jamestown",
      "conference": "nsic",
      "games": 28,
      "adjO": 111.85787225174533,
      "adjD": 112.17137293086661,
      "adjEM": -0.313500679121276,
      "adjT": 68.55
    },
    {
      "teamId": "1134",
      "team": "Lane",
      "conference": "siac",
      "games": 26,
      "adjO": 98.75454645651935,
      "adjD": 99.12992472382443,
      "adjEM": -0.3753782673050807,
      "adjT": 78.51634615384616
    },
    {
      "teamId": "1011",
      "team": "Claflin",
      "conference": "ciaa",
      "games": 25,
      "adjO": 100.23772311167734,
      "adjD": 100.85499451587752,
      "adjEM": -0.6172714042001815,
      "adjT": 76.139
    },
    {
      "teamId": "1437",
      "team": "CSUSB",
      "conference": "ccaa",
      "games": 25,
      "adjO": 106.22996274153019,
      "adjD": 106.91196251138977,
      "adjEM": -0.681999769859587,
      "adjT": 69.24600000000001
    },
    {
      "teamId": "2245",
      "team": "Georgia College",
      "conference": "peach-belt",
      "games": 28,
      "adjO": 107.26635112931311,
      "adjD": 108.08315210127934,
      "adjEM": -0.8168009719662308,
      "adjT": 72.81607142857142
    },
    {
      "teamId": "661",
      "team": "Central St. (OH)",
      "conference": "siac",
      "games": 30,
      "adjO": 100.80369257889059,
      "adjD": 101.66662803365708,
      "adjEM": -0.862935454766486,
      "adjT": 71.85583333333334
    },
    {
      "teamId": "261812",
      "team": "Okla. Christian",
      "conference": "lone-star",
      "games": 25,
      "adjO": 102.55843204467237,
      "adjD": 103.45591493132477,
      "adjEM": -0.8974828866523978,
      "adjT": 72.34899999999999
    },
    {
      "teamId": "1575",
      "team": "Wis.-Parkside",
      "conference": "gliac",
      "games": 27,
      "adjO": 106.59667354099152,
      "adjD": 107.92507591841122,
      "adjEM": -1.3284023774197067,
      "adjT": 69.14259259259259
    },
    {
      "teamId": "2727",
      "team": "N.M. Highlands",
      "conference": "rmac",
      "games": 28,
      "adjO": 105.19461727680508,
      "adjD": 106.72032583397983,
      "adjEM": -1.5257085571747524,
      "adjT": 74.04642857142858
    },
    {
      "teamId": "867",
      "team": "Caldwell",
      "conference": "cacc",
      "games": 27,
      "adjO": 104.06259780907668,
      "adjD": 105.6147525368623,
      "adjEM": -1.55215472778562,
      "adjT": 73.95833333333333
    },
    {
      "teamId": "1330",
      "team": "Southern Conn. St.",
      "conference": "ne10",
      "games": 26,
      "adjO": 101.00721887750734,
      "adjD": 102.78176082592488,
      "adjEM": -1.7745419484175358,
      "adjT": 67.39807692307691
    },
    {
      "teamId": "2220",
      "team": "Bemidji St.",
      "conference": "nsic",
      "games": 27,
      "adjO": 110.77782374844848,
      "adjD": 112.59956553222301,
      "adjEM": -1.8217417837745273,
      "adjT": 71.6148148148148
    },
    {
      "teamId": "1685",
      "team": "Shippensburg",
      "conference": "psac",
      "games": 27,
      "adjO": 106.78362265934818,
      "adjD": 108.64054082602725,
      "adjEM": -1.8569181666790655,
      "adjT": 70.51296296296296
    },
    {
      "teamId": "1924",
      "team": "MSU Moorhead",
      "conference": "nsic",
      "games": 29,
      "adjO": 113.388573920628,
      "adjD": 115.39024747400792,
      "adjEM": -2.0016735533799164,
      "adjT": 71.16206896551724
    },
    {
      "teamId": "1216",
      "team": "Concord",
      "conference": "mec",
      "games": 28,
      "adjO": 110.04515348592099,
      "adjD": 112.15892771661082,
      "adjEM": -2.1137742306898275,
      "adjT": 74.54732142857142
    },
    {
      "teamId": "2610",
      "team": "Truman St.",
      "conference": "glvc",
      "games": 27,
      "adjO": 106.94610317062833,
      "adjD": 109.11554538598219,
      "adjEM": -2.169442215353854,
      "adjT": 72.10277777777777
    },
    {
      "teamId": "1228",
      "team": "Henderson St.",
      "conference": "gac",
      "games": 27,
      "adjO": 101.2039966913068,
      "adjD": 103.4473635473715,
      "adjEM": -2.2433668560646964,
      "adjT": 70.5212962962963
    },
    {
      "teamId": "16436",
      "team": "Minot St.",
      "conference": "nsic",
      "games": 29,
      "adjO": 108.3150174104166,
      "adjD": 110.71965310798493,
      "adjEM": -2.404635697568324,
      "adjT": 69.81551724137931
    },
    {
      "teamId": "2254",
      "team": "Northern St.",
      "conference": "nsic",
      "games": 29,
      "adjO": 106.29960815834423,
      "adjD": 108.70633910226513,
      "adjEM": -2.4067309439209055,
      "adjT": 68.64137931034483
    },
    {
      "teamId": "1298",
      "team": "Quincy",
      "conference": "glvc",
      "games": 27,
      "adjO": 105.59566787003611,
      "adjD": 108.04106299316496,
      "adjEM": -2.445395123128847,
      "adjT": 69.76296296296296
    },
    {
      "teamId": "1960",
      "team": "Northwest Mo. St.",
      "conference": "mid-america-intercollegiate",
      "games": 27,
      "adjO": 100.11140762235406,
      "adjD": 102.92711912573952,
      "adjEM": -2.815711503385458,
      "adjT": 71.47592592592592
    },
    {
      "teamId": "261800",
      "team": "Shorter",
      "conference": "conference-carolinas",
      "games": 26,
      "adjO": 110.44449425757196,
      "adjD": 113.57260834229083,
      "adjEM": -3.1281140847188738,
      "adjT": 72.92211538461538
    },
    {
      "teamId": "1916",
      "team": "Holy Family",
      "conference": "cacc",
      "games": 28,
      "adjO": 104.10965750771575,
      "adjD": 107.34698512434232,
      "adjEM": -3.2373276166265725,
      "adjT": 71.45625
    },
    {
      "teamId": "2452",
      "team": "Emory & Henry",
      "conference": "sac",
      "games": 27,
      "adjO": 105.7291531830067,
      "adjD": 108.99112684002668,
      "adjEM": -3.261973657019979,
      "adjT": 71.53148148148148
    },
    {
      "teamId": "2585",
      "team": "Post",
      "conference": "cacc",
      "games": 27,
      "adjO": 102.04854883932406,
      "adjD": 105.36384001610915,
      "adjEM": -3.315291176785095,
      "adjT": 73.31296296296297
    },
    {
      "teamId": "2670",
      "team": "Tex. A&M-Kingsville",
      "conference": "lone-star",
      "games": 27,
      "adjO": 98.53372434017595,
      "adjD": 101.91742513497069,
      "adjEM": -3.383700794794734,
      "adjT": 71.04166666666667
    },
    {
      "teamId": "1388990",
      "team": "UC Merced",
      "conference": "ccaa",
      "games": 26,
      "adjO": 98.41894551129809,
      "adjD": 101.81389491734319,
      "adjEM": -3.3949494060451,
      "adjT": 70.85096153846153
    },
    {
      "teamId": "1756",
      "team": "Colo. Christian",
      "conference": "rmac",
      "games": 28,
      "adjO": 103.67339492578932,
      "adjD": 107.16235538801509,
      "adjEM": -3.488960462225762,
      "adjT": 68.51875
    },
    {
      "teamId": "52014",
      "team": "King (TN)",
      "conference": "conference-carolinas",
      "games": 28,
      "adjO": 105.21332486576986,
      "adjD": 108.74346829285322,
      "adjEM": -3.5301434270833596,
      "adjT": 77.32589285714286
    },
    {
      "teamId": "1387965",
      "team": "Converse",
      "conference": "conference-carolinas",
      "games": 25,
      "adjO": 111.23648465285018,
      "adjD": 114.77852272076099,
      "adjEM": -3.542038067910809,
      "adjT": 70.013
    },
    {
      "teamId": "1607",
      "team": "Southern Ark.",
      "conference": "gac",
      "games": 27,
      "adjO": 103.72361451498142,
      "adjD": 107.28475072926705,
      "adjEM": -3.561136214285625,
      "adjT": 70.27222222222223
    },
    {
      "teamId": "404",
      "team": "Hillsdale",
      "conference": "g-mac",
      "games": 27,
      "adjO": 104.77489768076398,
      "adjD": 108.36908391155006,
      "adjEM": -3.594186230786079,
      "adjT": 67.87037037037037
    },
    {
      "teamId": "32",
      "team": "Delta St.",
      "conference": "gulf-south",
      "games": 27,
      "adjO": 107.9411081188227,
      "adjD": 111.54449426037228,
      "adjEM": -3.603386141549578,
      "adjT": 67.73240740740741
    },
    {
      "teamId": "16498",
      "team": "Fresno Pacific",
      "conference": "pacwest",
      "games": 27,
      "adjO": 99.50613725978228,
      "adjD": 103.17886168221852,
      "adjEM": -3.6727244224362465,
      "adjT": 70.68240740740741
    },
    {
      "teamId": "261797",
      "team": "Union (TN)",
      "conference": "gulf-south",
      "games": 28,
      "adjO": 108.85781759568167,
      "adjD": 112.54167863431448,
      "adjEM": -3.683861038632813,
      "adjT": 71.45625
    },
    {
      "teamId": "1120",
      "team": "Cal Poly Humboldt",
      "conference": "ccaa",
      "games": 27,
      "adjO": 105.65596738423129,
      "adjD": 109.4116393093157,
      "adjEM": -3.755671925084414,
      "adjT": 69.72314814814816
    },
    {
      "teamId": "1790",
      "team": "Ferris St.",
      "conference": "gliac",
      "games": 26,
      "adjO": 104.29007836366051,
      "adjD": 108.1892126668246,
      "adjEM": -3.8991343031640895,
      "adjT": 72.39423076923077
    },
    {
      "teamId": "2731",
      "team": "Tusculum",
      "conference": "sac",
      "games": 28,
      "adjO": 106.14581241213095,
      "adjD": 110.04507567172823,
      "adjEM": -3.8992632595972765,
      "adjT": 71.12857142857142
    },
    {
      "teamId": "1460",
      "team": "Davis & Elkins",
      "conference": "mec",
      "games": 27,
      "adjO": 107.19439290867861,
      "adjD": 111.2970102567833,
      "adjEM": -4.102617348104687,
      "adjT": 76.35833333333333
    },
    {
      "teamId": "261799",
      "team": "Azusa Pacific",
      "conference": "pacwest",
      "games": 26,
      "adjO": 99.85516787360106,
      "adjD": 104.14514633823335,
      "adjEM": -4.289978464632284,
      "adjT": 73.02884615384616
    },
    {
      "teamId": "162",
      "team": "Emporia St.",
      "conference": "mid-america-intercollegiate",
      "games": 27,
      "adjO": 105.89506856093654,
      "adjD": 110.59592180831446,
      "adjEM": -4.700853247377921,
      "adjT": 71.10462962962963
    },
    {
      "teamId": "1072",
      "team": "Chaminade",
      "conference": "pacwest",
      "games": 27,
      "adjO": 100.85882105164627,
      "adjD": 105.5802007938361,
      "adjEM": -4.721379742189825,
      "adjT": 79.1351851851852
    },
    {
      "teamId": "896",
      "team": "Wilmington (DE)",
      "conference": "cacc",
      "games": 27,
      "adjO": 104.0879380593065,
      "adjD": 108.8472515200397,
      "adjEM": -4.75931346073321,
      "adjT": 75.22129629629629
    },
    {
      "teamId": "2422",
      "team": "Clarion",
      "conference": "psac",
      "games": 27,
      "adjO": 107.37828995556423,
      "adjD": 112.15925128128946,
      "adjEM": -4.7809613257252295,
      "adjT": 75.84814814814816
    },
    {
      "teamId": "143",
      "team": "Winston-Salem",
      "conference": "ciaa",
      "games": 26,
      "adjO": 98.11021540901282,
      "adjD": 102.97771591367355,
      "adjEM": -4.867500504660725,
      "adjT": 72.75961538461539
    },
    {
      "teamId": "2581",
      "team": "Mount Olive",
      "conference": "conference-carolinas",
      "games": 28,
      "adjO": 112.08482094558043,
      "adjD": 117.23112183941677,
      "adjEM": -5.14630089383634,
      "adjT": 74.27410714285715
    },
    {
      "teamId": "2088",
      "team": "Chico St.",
      "conference": "ccaa",
      "games": 26,
      "adjO": 103.74159114916328,
      "adjD": 109.17079765660208,
      "adjEM": -5.429206507438792,
      "adjT": 69.18076923076923
    },
    {
      "teamId": "677",
      "team": "Ark.-Monticello",
      "conference": "gac",
      "games": 27,
      "adjO": 98.82787525751226,
      "adjD": 104.2836928090562,
      "adjEM": -5.455817551543944,
      "adjT": 65.17129629629629
    },
    {
      "teamId": "1238",
      "team": "Newberry",
      "conference": "sac",
      "games": 27,
      "adjO": 104.60765587796645,
      "adjD": 110.19689282616125,
      "adjEM": -5.589236948194795,
      "adjT": 70.77592592592593
    },
    {
      "teamId": "1015",
      "team": "UT Permian Basin",
      "conference": "lone-star",
      "games": 27,
      "adjO": 107.06207589846694,
      "adjD": 112.71658064434713,
      "adjEM": -5.654504745880189,
      "adjT": 73.68518518518519
    },
    {
      "teamId": "1595",
      "team": "Neb.-Kearney",
      "conference": "mid-america-intercollegiate",
      "games": 27,
      "adjO": 104.44674250258532,
      "adjD": 110.10162850495897,
      "adjEM": -5.654886002373644,
      "adjT": 75.21111111111111
    },
    {
      "teamId": "2370",
      "team": "Texas-Dallas",
      "conference": "lone-star",
      "games": 27,
      "adjO": 102.8712079881244,
      "adjD": 108.68212130835187,
      "adjEM": -5.8109133202274705,
      "adjT": 72.9787037037037
    },
    {
      "teamId": "2167",
      "team": "Johnson C. Smith",
      "conference": "ciaa",
      "games": 28,
      "adjO": 100.58253850005497,
      "adjD": 106.39579925970561,
      "adjEM": -5.813260759650646,
      "adjT": 73.10982142857144
    },
    {
      "teamId": "2510",
      "team": "MSU Denver",
      "conference": "rmac",
      "games": 27,
      "adjO": 104.09314125670363,
      "adjD": 110.23089919279143,
      "adjEM": -6.1377579360877945,
      "adjT": 73.72314814814816
    },
    {
      "teamId": "1582",
      "team": "Arkansas Tech",
      "conference": "gac",
      "games": 28,
      "adjO": 97.97090657660293,
      "adjD": 104.23194383849601,
      "adjEM": -6.26103726189308,
      "adjT": 67.14821428571429
    },
    {
      "teamId": "1588",
      "team": "D'Youville",
      "conference": "ecc",
      "games": 23,
      "adjO": 100.31943365276699,
      "adjD": 106.63706107576469,
      "adjEM": -6.3176274229977025,
      "adjT": 75.54130434782608
    },
    {
      "teamId": "1765",
      "team": "Cal State LA",
      "conference": "ccaa",
      "games": 27,
      "adjO": 102.12192657460423,
      "adjD": 108.47622522193848,
      "adjEM": -6.354298647334247,
      "adjT": 68.72685185185185
    },
    {
      "teamId": "261791",
      "team": "Northwestern Okla.",
      "conference": "gac",
      "games": 27,
      "adjO": 96.59881148059173,
      "adjD": 103.00364077669903,
      "adjEM": -6.404829296107295,
      "adjT": 73.23148148148148
    },
    {
      "teamId": "52018",
      "team": "Simon Fraser",
      "conference": "great-northwest",
      "games": 24,
      "adjO": 106.3110617215354,
      "adjD": 112.72900969198294,
      "adjEM": -6.417947970447543,
      "adjT": 67.49062500000001
    },
    {
      "teamId": "666",
      "team": "Belmont Abbey",
      "conference": "conference-carolinas",
      "games": 26,
      "adjO": 101.47515855493523,
      "adjD": 108.22571985645257,
      "adjEM": -6.750561301517337,
      "adjT": 68.37596153846154
    },
    {
      "teamId": "651",
      "team": "Chestnut Hill",
      "conference": "cacc",
      "games": 26,
      "adjO": 98.7713102937481,
      "adjD": 105.55562871176308,
      "adjEM": -6.784318418014976,
      "adjT": 72.70096153846154
    },
    {
      "teamId": "2492",
      "team": "Livingstone",
      "conference": "ciaa",
      "games": 27,
      "adjO": 94.69966368118422,
      "adjD": 101.60537456729668,
      "adjEM": -6.905710886112459,
      "adjT": 76.81203703703704
    },
    {
      "teamId": "785",
      "team": "Lincoln (PA)",
      "conference": "ciaa",
      "games": 30,
      "adjO": 97.38757008230944,
      "adjD": 104.92505353319058,
      "adjEM": -7.53748345088114,
      "adjT": 69.85833333333333
    },
    {
      "teamId": "893",
      "team": "Western Ore.",
      "conference": "great-northwest",
      "games": 26,
      "adjO": 103.76166114956365,
      "adjD": 111.33761016847532,
      "adjEM": -7.575949018911672,
      "adjT": 63.90384615384615
    },
    {
      "teamId": "1793",
      "team": "Florida Tech",
      "conference": "sunshine-state",
      "games": 27,
      "adjO": 105.60212635452872,
      "adjD": 113.18596107643613,
      "adjEM": -7.583834721907408,
      "adjT": 72.45925925925927
    },
    {
      "teamId": "261813",
      "team": "Southern Wesleyan",
      "conference": "conference-carolinas",
      "games": 30,
      "adjO": 110.95510276282185,
      "adjD": 118.59957690475926,
      "adjEM": -7.644474141937408,
      "adjT": 75.37583333333333
    },
    {
      "teamId": "2252",
      "team": "Midwestern St.",
      "conference": "lone-star",
      "games": 27,
      "adjO": 98.0853043435679,
      "adjD": 105.83860720529931,
      "adjEM": -7.753302861731413,
      "adjT": 75.63333333333333
    },
    {
      "teamId": "346",
      "team": "Lees-McRae",
      "conference": "conference-carolinas",
      "games": 28,
      "adjO": 101.84304614236359,
      "adjD": 109.93083901600029,
      "adjEM": -8.087792873636701,
      "adjT": 74.16875
    },
    {
      "teamId": "2174",
      "team": "Lock Haven",
      "conference": "psac",
      "games": 26,
      "adjO": 100.11282144385511,
      "adjD": 108.34016313468369,
      "adjEM": -8.227341690828581,
      "adjT": 74.14711538461539
    },
    {
      "teamId": "1389244",
      "team": "Middle Georgia",
      "conference": "peach-belt",
      "games": 26,
      "adjO": 102.25352844852233,
      "adjD": 110.75817538012913,
      "adjEM": -8.5046469316068,
      "adjT": 73.98653846153846
    },
    {
      "teamId": "819",
      "team": "Albany St. (GA)",
      "conference": "siac",
      "games": 29,
      "adjO": 101.93241904489084,
      "adjD": 110.52067141428384,
      "adjEM": -8.588252369393004,
      "adjT": 72.22500000000001
    },
    {
      "teamId": "1387966",
      "team": "Allen",
      "conference": "siac",
      "games": 26,
      "adjO": 97.20138637421758,
      "adjD": 105.83133777749012,
      "adjEM": -8.629951403272543,
      "adjT": 74.35
    },
    {
      "teamId": "806",
      "team": "Mississippi Col.",
      "conference": "gulf-south",
      "games": 28,
      "adjO": 103.77088898552525,
      "adjD": 112.46185401971083,
      "adjEM": -8.69096503418558,
      "adjT": 71.86160714285714
    },
    {
      "teamId": "261809",
      "team": "South Dakota Mines",
      "conference": "rmac",
      "games": 27,
      "adjO": 102.34371095897257,
      "adjD": 111.13345061573258,
      "adjEM": -8.78973965676002,
      "adjT": 74.1148148148148
    },
    {
      "teamId": "810",
      "team": "Molloy",
      "conference": "ecc",
      "games": 25,
      "adjO": 101.29834149781512,
      "adjD": 110.25663616568701,
      "adjEM": -8.958294667871897,
      "adjT": 79.40899999999999
    },
    {
      "teamId": "2062",
      "team": "Mary",
      "conference": "nsic",
      "games": 28,
      "adjO": 100.09587262290505,
      "adjD": 109.25593360190263,
      "adjEM": -9.160060978997578,
      "adjT": 73.57232142857143
    },
    {
      "teamId": "2722",
      "team": "Western Colo.",
      "conference": "rmac",
      "games": 27,
      "adjO": 104.42900007693687,
      "adjD": 113.68808653182296,
      "adjEM": -9.259086454886088,
      "adjT": 72.20925925925927
    },
    {
      "teamId": "261798",
      "team": "Roberts Wesleyan",
      "conference": "ecc",
      "games": 24,
      "adjO": 101.88128402068185,
      "adjD": 111.22842138459639,
      "adjEM": -9.347137363914541,
      "adjT": 76.35520833333334
    },
    {
      "teamId": "2568",
      "team": "Francis Marion",
      "conference": "conference-carolinas",
      "games": 28,
      "adjO": 102.49455765318869,
      "adjD": 112.40726162360744,
      "adjEM": -9.912703970418747,
      "adjT": 75.05624999999999
    },
    {
      "teamId": "395",
      "team": "Franklin Pierce",
      "conference": "ne10",
      "games": 29,
      "adjO": 98.72995272086771,
      "adjD": 108.68658790826964,
      "adjEM": -9.956635187401929,
      "adjT": 74.39310344827587
    },
    {
      "teamId": "2539",
      "team": "Bowie St.",
      "conference": "ciaa",
      "games": 30,
      "adjO": 93.96814032575621,
      "adjD": 104.00215362526919,
      "adjEM": -10.034013299512978,
      "adjT": 74.49333333333334
    },
    {
      "teamId": "177",
      "team": "Mars Hill",
      "conference": "sac",
      "games": 27,
      "adjO": 98.55123189039864,
      "adjD": 108.63303017723939,
      "adjEM": -10.081798286840751,
      "adjT": 74.07314814814815
    },
    {
      "teamId": "79",
      "team": "Kutztown",
      "conference": "psac",
      "games": 25,
      "adjO": 97.03125876873,
      "adjD": 107.41831440190717,
      "adjEM": -10.38705563317717,
      "adjT": 71.27600000000001
    },
    {
      "teamId": "1977",
      "team": "Queens (NY)",
      "conference": "ecc",
      "games": 26,
      "adjO": 96.09224855861626,
      "adjD": 106.59859604339503,
      "adjEM": -10.506347484778772,
      "adjT": 75.04807692307692
    },
    {
      "teamId": "159",
      "team": "Christian Brothers",
      "conference": "gulf-south",
      "games": 27,
      "adjO": 101.8110346764004,
      "adjD": 112.40969568491815,
      "adjEM": -10.598661008517752,
      "adjT": 65.95370370370371
    },
    {
      "teamId": "261814",
      "team": "Georgian Court",
      "conference": "cacc",
      "games": 28,
      "adjO": 95.63394958376752,
      "adjD": 106.52587807926368,
      "adjEM": -10.89192849549616,
      "adjT": 76.25803571428571
    },
    {
      "teamId": "1842",
      "team": "Menlo",
      "conference": "pacwest",
      "games": 27,
      "adjO": 98.26612016912117,
      "adjD": 109.4217057674142,
      "adjEM": -11.15558559829303,
      "adjT": 71.61203703703704
    },
    {
      "teamId": "1606",
      "team": "Southeastern Okla.",
      "conference": "gac",
      "games": 27,
      "adjO": 106.18459696045166,
      "adjD": 117.43787428343835,
      "adjEM": -11.25327732298669,
      "adjT": 64.9462962962963
    },
    {
      "teamId": "2260",
      "team": "Tiffin",
      "conference": "g-mac",
      "games": 27,
      "adjO": 91.56652710564951,
      "adjD": 102.99492662702528,
      "adjEM": -11.428399521375766,
      "adjT": 68.1148148148148
    },
    {
      "teamId": "2701",
      "team": "Minn.-Crookston",
      "conference": "nsic",
      "games": 29,
      "adjO": 100.6768996091143,
      "adjD": 112.30608165984582,
      "adjEM": -11.629182050731515,
      "adjT": 72.33793103448276
    },
    {
      "teamId": "1879",
      "team": "Winona St.",
      "conference": "nsic",
      "games": 28,
      "adjO": 100.09914733293674,
      "adjD": 111.75116740058803,
      "adjEM": -11.652020067651293,
      "adjT": 67.54017857142857
    },
    {
      "teamId": "1250",
      "team": "West Virginia St.",
      "conference": "mec",
      "games": 27,
      "adjO": 105.74397084230705,
      "adjD": 117.52921535893155,
      "adjEM": -11.785244516624502,
      "adjT": 78.2462962962963
    },
    {
      "teamId": "2123",
      "team": "Dist. Columbia",
      "conference": "ecc",
      "games": 23,
      "adjO": 95.39925659160266,
      "adjD": 107.20615570829553,
      "adjEM": -11.806899116692861,
      "adjT": 75.15326086956522
    },
    {
      "teamId": "1023",
      "team": "Hawaii Hilo",
      "conference": "pacwest",
      "games": 29,
      "adjO": 97.80333408993468,
      "adjD": 109.84672257918496,
      "adjEM": -12.043388489250276,
      "adjT": 68.36379310344827
    },
    {
      "teamId": "2447",
      "team": "Elizabeth City St.",
      "conference": "ciaa",
      "games": 24,
      "adjO": 90.21125030704987,
      "adjD": 102.5364274150027,
      "adjEM": -12.32517710795284,
      "adjT": 67.85000000000001
    },
    {
      "teamId": "2240",
      "team": "Cameron",
      "conference": "lone-star",
      "games": 28,
      "adjO": 99.20033818297107,
      "adjD": 112.06704304041128,
      "adjEM": -12.866704857440212,
      "adjT": 76.03660714285715
    },
    {
      "teamId": "2712",
      "team": "Tex. A&M Int'l",
      "conference": "lone-star",
      "games": 27,
      "adjO": 98.03553721223166,
      "adjD": 111.03452936009191,
      "adjEM": -12.99899214786025,
      "adjT": 69.09814814814816
    },
    {
      "teamId": "2242",
      "team": "Chadron St.",
      "conference": "rmac",
      "games": 27,
      "adjO": 100.66462167689161,
      "adjD": 113.90711600942855,
      "adjEM": -13.242494332536936,
      "adjT": 72.44444444444444
    },
    {
      "teamId": "319",
      "team": "Newman",
      "conference": "mid-america-intercollegiate",
      "games": 27,
      "adjO": 100.62099257838138,
      "adjD": 114.2279504675259,
      "adjEM": -13.606957889144525,
      "adjT": 73.35925925925926
    },
    {
      "teamId": "261792",
      "team": "Spring Hill",
      "conference": "siac",
      "games": 28,
      "adjO": 98.72278311640919,
      "adjD": 112.9251700680272,
      "adjEM": -14.20238695161801,
      "adjT": 73.40178571428571
    },
    {
      "teamId": "1547",
      "team": "American Int'l",
      "conference": "ne10",
      "games": 28,
      "adjO": 94.64709409954892,
      "adjD": 108.98565978160768,
      "adjEM": -14.338565682058757,
      "adjT": 68.4875
    },
    {
      "teamId": "1388963",
      "team": "Point Park",
      "conference": "mec",
      "games": 25,
      "adjO": 106.6922306965728,
      "adjD": 121.15732368896926,
      "adjEM": -14.46509299239645,
      "adjT": 70.933
    },
    {
      "teamId": "1826",
      "team": "Kentucky St.",
      "conference": "siac",
      "games": 28,
      "adjO": 89.86823216349015,
      "adjD": 105.43726412896612,
      "adjEM": -15.569031965475972,
      "adjT": 76.50089285714286
    },
    {
      "teamId": "1939",
      "team": "Sul Ross St.",
      "conference": "lone-star",
      "games": 25,
      "adjO": 90.19109687396444,
      "adjD": 105.85065434949964,
      "adjEM": -15.659557475535195,
      "adjT": 72.42399999999999
    },
    {
      "teamId": "596",
      "team": "Saint Leo",
      "conference": "sunshine-state",
      "games": 28,
      "adjO": 101.60856305686778,
      "adjD": 117.32582551606131,
      "adjEM": -15.717262459193535,
      "adjT": 74.65625
    },
    {
      "teamId": "2491",
      "team": "Lewis",
      "conference": "glvc",
      "games": 27,
      "adjO": 93.30884570050164,
      "adjD": 109.0289608177172,
      "adjEM": -15.72011511721557,
      "adjT": 67.55740740740741
    },
    {
      "teamId": "2039",
      "team": "Salem (WV)",
      "conference": "dii-independent",
      "games": 26,
      "adjO": 99.69458720209987,
      "adjD": 116.58053455357253,
      "adjEM": -16.885947351472666,
      "adjT": 78.39326923076922
    },
    {
      "teamId": "872",
      "team": "Coker",
      "conference": "sac",
      "games": 27,
      "adjO": 97.93388954499854,
      "adjD": 114.98112683524168,
      "adjEM": -17.047237290243146,
      "adjT": 72.91388888888889
    },
    {
      "teamId": "16383",
      "team": "AUM",
      "conference": "gulf-south",
      "games": 29,
      "adjO": 98.32983876798495,
      "adjD": 115.66369445146385,
      "adjEM": -17.3338556834789,
      "adjT": 71.5396551724138
    },
    {
      "teamId": "1156",
      "team": "Mercy",
      "conference": "ecc",
      "games": 26,
      "adjO": 92.04884938938262,
      "adjD": 109.41943277046582,
      "adjEM": -17.370583381083193,
      "adjT": 76.92403846153846
    },
    {
      "teamId": "1388736",
      "team": "Roosevelt",
      "conference": "gliac",
      "games": 26,
      "adjO": 97.13482302515732,
      "adjD": 115.17454609842139,
      "adjEM": -18.03972307326407,
      "adjT": 70.44134615384615
    },
    {
      "teamId": "1563",
      "team": "Bloomsburg",
      "conference": "psac",
      "games": 28,
      "adjO": 89.20002545662827,
      "adjD": 107.82024910717665,
      "adjEM": -18.620223650548382,
      "adjT": 70.14732142857143
    },
    {
      "teamId": "259",
      "team": "San Fran. St.",
      "conference": "ccaa",
      "games": 28,
      "adjO": 95.50098029099165,
      "adjD": 116.54897303159008,
      "adjEM": -21.04799274059843,
      "adjT": 69.22142857142858
    },
    {
      "teamId": "996",
      "team": "Clayton St.",
      "conference": "peach-belt",
      "games": 27,
      "adjO": 97.5585326155002,
      "adjD": 119.2921730187993,
      "adjEM": -21.733640403299106,
      "adjT": 73.95370370370371
    },
    {
      "teamId": "1530",
      "team": "Mansfield",
      "conference": "psac",
      "games": 26,
      "adjO": 95.8169285068104,
      "adjD": 120.71120634677688,
      "adjEM": -24.894277839966477,
      "adjT": 75.46442307692308
    },
    {
      "teamId": "2187",
      "team": "Maryville (MO)",
      "conference": "glvc",
      "games": 28,
      "adjO": 96.32439949739549,
      "adjD": 121.41924302156693,
      "adjEM": -25.094843524171438,
      "adjT": 73.19017857142856
    },
    {
      "teamId": "687",
      "team": "West Va. Wesleyan",
      "conference": "mec",
      "games": 26,
      "adjO": 93.65198998322433,
      "adjD": 121.02741646450733,
      "adjEM": -27.375426481283,
      "adjT": 79.09807692307693
    },
    {
      "teamId": "2306",
      "team": "Regis (CO)",
      "conference": "rmac",
      "games": 25,
      "adjO": 96.13498136158525,
      "adjD": 128.17253565392298,
      "adjEM": -32.03755429233773,
      "adjT": 71.358
    },
    {
      "teamId": "2244",
      "team": "Erskine",
      "conference": "conference-carolinas",
      "games": 27,
      "adjO": 84.96723045849878,
      "adjD": 119.23240703855822,
      "adjEM": -34.265176580059446,
      "adjT": 67.38981481481481
    },
    {
      "teamId": "51863",
      "team": "P.R.-Bayamon",
      "conference": "dii-independent",
      "games": 9,
      "adjO": 85.08325893723556,
      "adjD": 122.77070063694266,
      "adjEM": -37.68744169970711,
      "adjT": 71.5638888888889
    },
    {
      "teamId": "51864",
      "team": "P.R.-Rio Piedras",
      "conference": "dii-independent",
      "games": 5,
      "adjO": 76.35753901715465,
      "adjD": 126.25135497035006,
      "adjEM": -49.893815953195414,
      "adjT": 77.53
    },
    {
      "teamId": "51861",
      "team": "P.R.-Mayaguez",
      "conference": "dii-independent",
      "games": 6,
      "adjO": 70.70970433331595,
      "adjD": 133.40270551508846,
      "adjEM": -62.6930011817725,
      "adjT": 79.90416666666667
    }
  ]
}